Workbook

Sheet Légende
A1: Cas de test QuickOrder V3.1 : mode d'emploi
A3: Rôle du fichier | B3: 24 cas de test : 6 nominaux, 6 limites, 6 erreurs, 6 règles métier. Les colonnes A à K sont rédigées. Les colonnes L à P sont à remplir pendant l'exécution.
A4: Colonnes à remplir | B4: L (Résultat obtenu), M (Statut), N (Preuve), O (Bug lié), P (Exécuté par / date). Elles sont en jaune avec une police bleue dans l'onglet Cas de test.
A5: Résultat obtenu | B5: Ce qui a été réellement constaté : messages, montants exacts, codes HTTP. Pas d'interprétation, pas de copier-coller du résultat attendu.
A6: Statut | B6: Pass : conforme à l'attendu. Fail : différent de l'attendu, un bug est à rédiger. Blocked : test impossible, indiquer la cause dans Résultat obtenu. Skipped : non exécuté volontairement, indiquer la raison. Laisser vide tant que le cas n'est pas passé.
A7: Preuve | B7: Chemin du fichier dans evidence/, par exemple evidence/TC-07_ui_01.png ou evidence/TC-14_api_01.txt. Plusieurs preuves : les séparer par une virgule.
A8: Bug lié | B8: Identifiant du bug rédigé dans bug-reports/, par exemple BUG-03. Obligatoire pour tout Fail. Un bug peut être lié à plusieurs cas.
A9: Avant chaque série | B9: Remettre la base à l'état initial (python seed.py, ou docker compose down -v puis relance). Plusieurs cas modifient le stock et créent des commandes.
A10: Ordre conseillé | B10: TC-14 et TC-03 en premier (identité de l'API), puis TC-12 et TC-18 (espèces), puis le reste. Les cas qui utilisent une commande existante le précisent dans leurs préconditions.
A11: Onglets suivants | B11: Synthèse : totaux calculés. Couverture risques : lien entre les risques de risk-matrix.md et les cas.
A13: Exemple de remplissage
A14: Exemple de format, valeurs fictives. Ne pas reprendre ces valeurs : elles ne viennent d'aucune exécution.
A15: Résultat obtenu | B15: Total affiché : 29,99 €. Message « Commande confirmée ». Commande #9 visible dans Mes commandes.
A16: Statut | B16: Fail
A17: Preuve | B17: evidence/TC-01_ui_01.png, evidence/TC-01_ui_02.png
A18: Bug lié | B18: BUG-07
A19: Exécuté par / date | B19: Prénom, 14/10/2026

Sheet Cas de test
A1: ID | B1: Famille | C1: Parcours | D1: Risque(s) | E1: Interface | F1: Titre | G1: Objectif | H1: Préconditions | I1: Données | J1: Étapes | K1: Résultat attendu | L1: Résultat obtenu | M1: Statut | N1: Preuve | O1: Bug lié | P1: Exécuté par / date
A2: TC-01 | B2: Nominal | C2: P1, P2 | D2: R-10, R-22 | E2: UI | F2: Commander et payer par carte | G2: Vérifier le parcours de commande complet d'un client connecté, du menu à la confirmation. | H2: Base à l'état initial. Alice connectée. Panier vide. | I2: Alice (alice@example.com). Burger Factory : 2 × Classic Burger (11,90 €) et 1 × Frites maison (3,50 €). Adresse par défaut, paiement par carte. | J2: 1. Ouvrir Burger Factory depuis la liste des restaurants. 2. Ajouter 2 Classic Burger, puis 1 Frites maison. 3. Ouvrir le panier, passer les frites à 2, lire le total, puis les remettre à 1 et cliquer sur Mettre à jour. 4. Cliquer sur Passer commande. 5. Vérifier l'adresse proposée, choisir Carte bancaire, confirmer. 6. Ouvrir Mes commandes, puis le détail de la nouvelle commande. | K2: Panier : sous-total 27,30 €, livraison 2,99 €, total 30,29 €. Le total suit la modification de quantité de l'étape 3. Message de confirmation. Commande au statut confirmed, paiement paid par carte, total 30,29 €. Panier vidé. Commande visible dans Mes commandes avec les bons articles et la bonne adresse.
A3: TC-02 | B3: Nominal | C3: P3 | D3: R-09, R-10 | E3: UI | F3: Appliquer un coupon valide au checkout | G3: Vérifier qu'un coupon valide réduit le total et que le montant se retrouve identique dans la commande. | H3: Alice connectée. Panier : 2 Classic Burger et 1 Frites maison (sous-total 27,30 €). | I3: Coupon WELCOME10, paiement par carte. | J3: 1. Cliquer sur Passer commande. 2. Saisir WELCOME10 dans le champ Coupon, cliquer sur Appliquer. 3. Lire le récapitulatif (sous-total, livraison, réduction, total). 4. Confirmer le paiement par carte. 5. Comparer le détail de la commande avec le récapitulatif de l'étape 3. | K3: Réduction de 2,73 € (10 % de 27,30 €). Total 27,56 €. Le détail de la commande reprend les mêmes montants : sous-total 27,30 €, livraison 2,99 €, réduction 2,73 €, total 27,56 €.
A4: TC-03 | B4: Nominal | C4: P4 | D4: R-01, R-19, R-20 | E4: API | F4: Créer une commande par l'API | G4: Vérifier la création d'une commande via POST /api/orders et la cohérence de la réponse avec l'interface. | H4: Swagger ou curl avec l'en-tête X-API-Key: quickorder-demo-key. Identifiant de Classic Burger relevé via GET /api/restaurants puis GET /api/restaurants/{id}/products. | I4: {"items":[{"product_id":<id Classic Burger>,"quantity":2}],"payment_method":"card"} | J4: 1. Relever l'identifiant de Classic Burger (Burger Factory). 2. Envoyer POST /api/orders avec le corps indiqué. 3. Envoyer GET /api/orders/{id renvoyé à l'étape 2}. 4. Dans l'interface, consulter Mes commandes avec Alice puis avec Bob, et noter à qui la commande est rattachée. | K4: Code 201. JSON avec status confirmed, payment_status paid, subtotal 23,80, delivery_fee 2,99, total 26,79 et une ligne d'article (quantité 2, line_total 23,80). Le GET de l'étape 3 renvoie la même commande. La commande est rattachée à un utilisateur identifié, celui qui a effectué l'appel.
A5: TC-04 | B5: Nominal | C5: P1 | D5: R-17 | E5: UI | F5: Rechercher, filtrer et trier les restaurants | G5: Vérifier que la recherche, la catégorie, le tri, le filtre de frais de livraison et le filtre végétarien renvoient ce que l'utilisateur demande. | H5: Page d'accueil, visiteur non connecté. | I5: Recherches : « Burger » et « salades ». Catégorie : Japonais. Tri : Livraison moins chère. Filtre : Livraison max ≤ 2,50 €, puis Végétarien. | J5: 1. Rechercher « Burger ». 2. Réinitialiser, choisir la catégorie Japonais. 3. Réinitialiser, trier par Livraison moins chère. 4. Réinitialiser, filtrer sur Livraison max ≤ 2,50 €. 5. Réinitialiser, cocher Végétarien. 6. Réinitialiser, rechercher « salades » (mot présent dans la description d'un restaurant, pas dans son nom). | K5: 1. Burger Factory seul. 2. Tokyo Bowl et Night Sushi (ce dernier marqué FERMÉ). 3. Frais croissants, de 1,99 € à 3,49 €. 4. Uniquement les restaurants à 2,50 € ou moins : Green Kitchen (1,99 €) et Pizza Roma (2,49 €). 5. Chaque restaurant affiché propose au moins un plat végétarien disponible. 6. Green Kitchen apparaît : un utilisateur qui tape un mot de la description s'attend à retrouver le restaurant.
A6: TC-05 | B6: Nominal | C6: P8 | D6: R-13, R-21 | E6: UI | F6: Créer un compte puis passer sa première commande | G6: Vérifier qu'un nouvel utilisateur peut s'inscrire et commander sans blocage ni incohérence, y compris sur l'adresse de livraison. | H6: Visiteur non connecté. Email jamais utilisé (par exemple test.qa01@example.com). | I6: Nom : Test QA. Mot de passe : Password123!. Green Kitchen : 1 × Chicken Caesar (12,50 €). Paiement par carte. | J6: 1. Ouvrir Créer un compte et s'inscrire avec les données ci-dessus. 2. Constater l'état de connexion (nom affiché dans l'en-tête). 3. Ouvrir Green Kitchen, ajouter 1 Chicken Caesar. 4. Passer commande et lire l'adresse proposée. 5. Tenter de confirmer avec l'adresse telle qu'elle est proposée. 6. Ouvrir Mon profil et lire la liste des adresses. 7. Si besoin, ajouter une adresse complète et refaire la commande. | K6: Compte créé, utilisateur connecté, nom visible. Une commande ne peut pas être confirmée avec une adresse vide ou incomplète : le client doit renseigner ou choisir une adresse complète (rue, code postal, ville). Avec une adresse valide, la commande est confirmée pour 14,49 € (12,50 € + 1,99 € de livraison). Le profil n'affiche pas d'adresse vide présentée comme valide.
A7: TC-06 | B7: Nominal | C7: P7 | D7: R-11 | E7: UI | F7: L'administrateur fait avancer le statut d'une commande | G7: Vérifier que les changements de statut faits par l'administrateur sont enregistrés et visibles côté client. | H7: Une commande confirmée d'Alice, créée pour ce test (ne pas réutiliser celle des autres cas). Admin connecté dans un navigateur, Alice dans une navigation privée. | I7: admin@quickorder.local / Admin123! Statuts : preparing, out_for_delivery, delivered. | J7: 1. Admin : ouvrir l'espace Admin et repérer la commande. 2. Passer la commande à preparing, cliquer sur Mettre à jour. 3. Côté Alice, recharger le détail de la commande. 4. Répéter pour out_for_delivery, puis delivered. | K7: Chaque changement affiche un message de confirmation et apparaît côté client au rechargement. Le tableau de bord admin montre le statut courant de la commande. La suite preparing, out_for_delivery, delivered est acceptée sans erreur.
A8: TC-07 | B8: Limite | C8: P6 | D8: R-05, R-22 | E8: UI | F8: Quantité égale au stock, puis au-delà | G8: Vérifier que le panier et la commande respectent le stock affiché, à la borne et au-dessus. | H8: Alice connectée, panier vide. Tokyo Bowl : Salmon Bowl affiché avec un stock de 2. | I8: Salmon Bowl (15,90 €). Quantités : 2, 3 et 5. | J8: 1. Ouvrir Tokyo Bowl, noter le stock affiché de Salmon Bowl. 2. Ajouter 2 Salmon Bowl. 3. Dans le panier, passer la quantité à 3 et cliquer sur Mettre à jour. 4. Vider le panier. Sur la page du restaurant, saisir 5 dans le champ quantité de Salmon Bowl et ajouter. 5. Tenter de passer commande avec le panier obtenu. 6. Revenir sur la page du restaurant, relever le stock affiché. | K8: 2 unités : acceptées. 3 et 5 unités : refusées, ou ramenées à 2, avec un message explicite. Le panier ne dépasse jamais le stock. Aucune commande n'est confirmée pour plus que le stock. Le stock affiché ne devient jamais négatif.
A9: TC-08 | B9: Limite | C9: P4 | D9: R-19 | E9: API | F9: Quantités extrêmes sur l'API | G9: Vérifier les bornes de quantité de POST /api/orders : nulle, négative, minimale, très grande. | H9: Clé API configurée. Identifiant de Chicken Caesar (Green Kitchen, 12,50 €) relevé via l'API. | I9: {"items":[{"product_id":<id Chicken Caesar>,"quantity":Q}],"payment_method":"card"} Q = 0, -1, 1, 1000. | J9: 1. Envoyer POST /api/orders avec Q = 0. 2. Idem avec Q = -1. 3. Idem avec Q = 1. 4. Idem avec Q = 1000. 5. Relever le stock de Chicken Caesar via GET /api/products/{id} avant et après la série. | K9: Q = 0 et Q = -1 : code 400 avec un message clair, aucune commande créée. Q = 1 : code 201, commande de 14,49 €. Q = 1000 : refusée (400 ou 409), aucune commande créée. Le stock ne baisse que pour la commande acceptée (une unité).
A10: TC-09 | B10: Limite | C10: P6 | D10: R-06 | E10: UI | F10: Minimum de commande : juste manqué, puis atteint | G10: Vérifier que le minimum de commande affiché par le restaurant est appliqué au moment de commander. | H10: Alice connectée, panier vide. Green Kitchen affiche « minimum 12,00 € ». | I10: 1 × Veggie Wrap (10,90 €), puis 1 × Chicken Caesar (12,50 €). Paiement par carte. | J10: 1. Ajouter 1 Veggie Wrap au panier. 2. Passer commande, choisir Carte bancaire, confirmer. 3. Noter le résultat et vérifier dans Mes commandes si une commande a été créée. 4. Vider le panier, ajouter 1 Chicken Caesar. 5. Passer commande, confirmer. | K10: Avec 10,90 € (sous le minimum de 12,00 €) : commande refusée avec un message qui indique le minimum, aucune commande créée. Avec 12,50 € : commande acceptée, total 14,49 €.
A11: TC-10 | B11: Limite | C11: P3 | D11: R-09 | E11: API | F11: Coupon : seuil du minimum d'achat et coupon expiré | G11: Vérifier le comportement de POST /api/coupons/validate autour du minimum d'achat, puis avec un coupon expiré. | H11: Clé API configurée. Minimum de WELCOME10 relevé en envoyant d'abord un sous-total de 1,00 (la réponse l'indique). | I11: WELCOME10 avec subtotal = minimum - 0,01, = minimum, = minimum + 0,01. Coupon expiré EXPIRED10 (relevé dans les données de démonstration) avec subtotal 50. | J11: 1. Envoyer un sous-total de 1,00 avec WELCOME10 et noter le minimum indiqué. 2. Envoyer minimum - 0,01. 3. Envoyer le minimum exact. 4. Envoyer minimum + 0,01. 5. Envoyer EXPIRED10 avec subtotal 50. | K11: Sous le minimum : valid false avec un message de minimum non atteint. Au minimum et au-dessus : valid true, discount égal à 10 % du subtotal arrondi au centime. Coupon expiré : refusé (valid false, message coupon invalide ou expiré), code HTTP conforme à la spécification OpenAPI (404).
A12: TC-11 | B12: Limite | C12: P3, P4 | D12: R-08, R-09, R-10 | E12: API | F12: Plafond de réduction et sous-total envoyé par l'appelant | G12: Vérifier que la réduction d'un coupon s'arrête à son plafond, et que l'API ne se laisse pas guider par un sous-total irréaliste. | H12: Clé API configurée. | I12: WELCOME10 avec subtotal = 50, 100, 500, 9999. | J12: 1. Envoyer POST /api/coupons/validate avec subtotal 50. 2. Idem avec 100. 3. Idem avec 500. 4. Idem avec 9999. 5. Comparer les réductions renvoyées avec 10 % du sous-total envoyé. | K12: La réduction croît avec le sous-total puis cesse de croître au plafond : les réponses pour 500 et 9999 sont égales au plafond, pas à 50,00 ni à 999,90. Une remise n'est jamais accordée au-delà du plafond du coupon, quel que soit le sous-total annoncé. Observation à noter : l'API calcule-t-elle sa réponse sur un montant qu'elle ne peut pas vérifier ? Un sous-total qui ne correspond à aucun panier réel ne doit pas permettre d'obtenir une remise exploitable à la commande.
A13: TC-12 | B13: Limite | C13: P2 | D13: R-02 | E13: UI | F13: Espèces : montant remis juste en dessous, égal, au-dessus du total | G13: Vérifier la règle du paiement en espèces autour du montant du total. | H13: Alice connectée. Panier : 2 Classic Burger et 1 Frites maison (total 30,29 €), à reconstituer après chaque commande acceptée. | I13: Paiement Espèces. Montant remis : 30,28 ; 30,29 ; 50,00 ; 0. | J13: 1. Au checkout, choisir Espèces et saisir 30,28, confirmer. 2. Saisir 30,29, confirmer. 3. Reconstituer le panier, saisir 50,00, confirmer. 4. Reconstituer le panier, saisir 0, confirmer. 5. Après chaque essai, consulter Mes commandes et le détail. | K13: 30,28 : refusé avec un message clair, aucune commande créée. 30,29 : accepté, monnaie 0,00 €. 50,00 : accepté, monnaie 19,71 €. 0 : refusé, aucune commande créée. Aucun montant remis inférieur au total ne donne une commande confirmée et payée.
... A25: TC-24 | B25: Règle métier | C25: P7 | D25: R-11 | E25: UI | F25: Statuts : pas de retour en arrière | G25: Vérifier que l'administrateur ne peut pas imposer une transition de statut incohérente. | H25: Admin connecté. Une commande delivered et une commande cancelled, créées pour ce test. | I25: Transitions testées : delivered vers confirmed, delivered vers cancelled, cancelled vers out_for_delivery. | J25: 1. Admin : choisir la commande delivered, la passer à confirmed. 2. La repasser de delivered à cancelled. 3. Choisir la commande cancelled, la passer à out_for_delivery. 4. Après chaque essai, consulter le statut côté client. | K25: Les trois transitions sont refusées avec un message explicite et le statut d'origine est conservé. Seules les transitions logiques sont acceptées : confirmed, preparing, out_for_delivery, delivered, et l'annulation avant la livraison.

Sheet Synthèse
A1: Synthèse de la campagne
A2: Tout est calculé à partir de la colonne Statut de l'onglet Cas de test. Rien à saisir ici.
A4: Famille | B4: Total | C4: Pass | D4: Fail | E4: Blocked | F4: Skipped | G4: Non exécuté
A5: Nominal | B5: =COUNTIF('Cas de test'!$B$2:$B$25,A5) -> 6 | C5: =COUNTIFS('Cas de test'!$B$2:$B$25,$A5,'Cas de test'!$M$2:$M$25,"Pass") -> 0 | D5: =COUNTIFS('Cas de test'!$B$2:$B$25,$A5,'Cas de test'!$M$2:$M$25,"Fail") -> 0 | E5: =COUNTIFS('Cas de test'!$B$2:$B$25,$A5,'Cas de test'!$M$2:$M$25,"Blocked") -> 0 | F5: =COUNTIFS('Cas de test'!$B$2:$B$25,$A5,'Cas de test'!$M$2:$M$25,"Skipped") -> 0 | G5: =B5-SUM(C5:F5) -> 6
A6: Limite | B6: =COUNTIF('Cas de test'!$B$2:$B$25,A6) -> 6 | C6: =COUNTIFS('Cas de test'!$B$2:$B$25,$A6,'Cas de test'!$M$2:$M$25,"Pass") -> 0 | D6: =COUNTIFS('Cas de test'!$B$2:$B$25,$A6,'Cas de test'!$M$2:$M$25,"Fail") -> 0 | E6: =COUNTIFS('Cas de test'!$B$2:$B$25,$A6,'Cas de test'!$M$2:$M$25,"Blocked") -> 0 | F6: =COUNTIFS('Cas de test'!$B$2:$B$25,$A6,'Cas de test'!$M$2:$M$25,"Skipped") -> 0 | G6: =B6-SUM(C6:F6) -> 6
A7: Erreur | B7: =COUNTIF('Cas de test'!$B$2:$B$25,A7) -> 6 | C7: =COUNTIFS('Cas de test'!$B$2:$B$25,$A7,'Cas de test'!$M$2:$M$25,"Pass") -> 0 | D7: =COUNTIFS('Cas de test'!$B$2:$B$25,$A7,'Cas de test'!$M$2:$M$25,"Fail") -> 0 | E7: =COUNTIFS('Cas de test'!$B$2:$B$25,$A7,'Cas de test'!$M$2:$M$25,"Blocked") -> 0 | F7: =COUNTIFS('Cas de test'!$B$2:$B$25,$A7,'Cas de test'!$M$2:$M$25,"Skipped") -> 0 | G7: =B7-SUM(C7:F7) -> 6
A8: Règle métier | B8: =COUNTIF('Cas de test'!$B$2:$B$25,A8) -> 6 | C8: =COUNTIFS('Cas de test'!$B$2:$B$25,$A8,'Cas de test'!$M$2:$M$25,"Pass") -> 0 | D8: =COUNTIFS('Cas de test'!$B$2:$B$25,$A8,'Cas de test'!$M$2:$M$25,"Fail") -> 0 | E8: =COUNTIFS('Cas de test'!$B$2:$B$25,$A8,'Cas de test'!$M$2:$M$25,"Blocked") -> 0 | F8: =COUNTIFS('Cas de test'!$B$2:$B$25,$A8,'Cas de test'!$M$2:$M$25,"Skipped") -> 0 | G8: =B8-SUM(C8:F8) -> 6
A9: Total | B9: =SUM(B5:B8) -> 24 | C9: =SUM(C5:C8) -> 0 | D9: =SUM(D5:D8) -> 0 | E9: =SUM(E5:E8) -> 0 | F9: =SUM(F5:F8) -> 0 | G9: =SUM(G5:G8) -> 24
A11: Indicateurs
A12: Cas rédigés | B12: =COUNTA('Cas de test'!$A$2:$A$25) -> 24
A13: Cas exécutés (Pass + Fail) | B13: =C9+D9 -> 0
A14: Taux de réussite sur les cas exécutés | B14: =IF(B13=0,"n/a",C9/B13) -> n/a
A15: Cas non encore statués | B15: =G9 -> 24
A16: Cas en Fail sans bug renseigné | B16: =COUNTIFS('Cas de test'!$M$2:$M$25,"Fail",'Cas de test'!$O$2:$O$25,"") -> 0
A17: Cohérence : total des familles = cas rédigés | B17: =IF(B9=B12,"OK","ÉCART") -> OK
A19: Les chiffres du rapport d'exécution et du récapitulatif des bugs doivent être identiques à ceux de cet onglet.

Sheet Couverture risques
A1: Couverture des risques par les cas de test
A2: Score et niveau repris de risk-matrix.md. Le nombre de cas est calculé à partir de la colonne Risque(s) de l'onglet Cas de test.
A4: Risque | B4: Intitulé | C4: Score | D4: Niveau | E4: Nb de cas | F4: Cas de test | G4: Remarque
A5: R-01 | B5: Identité des appels API (accès sans authentification utilisateur) | C5: 9 | D5: Critique | E5: =COUNTIF('Cas de test'!$D$2:$D$25,"*"&A5&"*") -> 2 | F5: TC-03, TC-14
A6: R-02 | B6: Paiement en espèces : montant remis et monnaie | C6: 9 | D6: Critique | E6: =COUNTIF('Cas de test'!$D$2:$D$25,"*"&A6&"*") -> 2 | F6: TC-12, TC-18
A7: R-03 | B7: Paiement PayPal : doublon de commande ou de débit | C7: 6 | D7: Critique | E7: =COUNTIF('Cas de test'!$D$2:$D$25,"*"&A7&"*") -> 1 | F7: TC-22
A8: R-04 | B8: Commande acceptée pour un restaurant fermé | C8: 6 | D8: Critique | E8: =COUNTIF('Cas de test'!$D$2:$D$25,"*"&A8&"*") -> 1 | F8: TC-19
A9: R-05 | B9: Commande acceptée avec stock nul ou insuffisant | C9: 6 | D9: Critique | E9: =COUNTIF('Cas de test'!$D$2:$D$25,"*"&A9&"*") -> 2 | F9: TC-07, TC-20
A10: R-10 | B10: Total faux : livraison, réduction, arrondi | C10: 6 | D10: Critique | E10: =COUNTIF('Cas de test'!$D$2:$D$25,"*"&A10&"*") -> 3 | F10: TC-01, TC-02, TC-11
A11: R-12 | B11: Conséquences d'une annulation (paiement, stock) | C11: 6 | D11: Critique | E11: =COUNTIF('Cas de test'!$D$2:$D$25,"*"&A11&"*") -> 1 | F11: TC-23
A12: R-07 | B12: Offre annoncée différente de la réduction appliquée | C12: 6 | D12: Critique | E12: =COUNTIF('Cas de test'!$D$2:$D$25,"*"&A12&"*") -> 1 | F12: TC-21
A13: R-11 | B13: Transitions de statut admin incohérentes | C13: 6 | D13: Critique | E13: =COUNTIF('Cas de test'!$D$2:$D$25,"*"&A13&"*") -> 2 | F13: TC-06, TC-24
A14: R-13 | B14: Première commande d'un nouvel utilisateur | C14: 6 | D14: Critique | E14: =COUNTIF('Cas de test'!$D$2:$D$25,"*"&A14&"*") -> 2 | F14: TC-05, TC-16
A15: R-06 | B15: Minimum de commande non appliqué | C15: 4 | D15: Élevé | E15: =COUNTIF('Cas de test'!$D$2:$D$25,"*"&A15&"*") -> 1 | F15: TC-09
A16: R-08 | B16: Sous-total fourni par l'appelant à la validation de coupon | C16: 4 | D16: Élevé | E16: =COUNTIF('Cas de test'!$D$2:$D$25,"*"&A16&"*") -> 1 | F16: TC-11
... A26: R-17 | B26: Recherche et filtres incohérents | C26: 3 | D26: Élevé | E26: =COUNTIF('Cas de test'!$D$2:$D$25,"*"&A26&"*") -> 1 | F26: TC-04
A27: R-18 | B27: Avis et favoris | C27: 2 | D27: Modéré | E27: =COUNTIF('Cas de test'!$D$2:$D$25,"*"&A27&"*") -> 0 | F27: aucun | G27: Pas de cas dédié : sessions exploratoires (dépôt d'avis sans commande, affichage des avis, favoris).
A28: R-24 | B28: Commander à nouveau | C28: 2 | D28: Modéré | E28: =COUNTIF('Cas de test'!$D$2:$D$25,"*"&A28&"*") -> 0 | F28: aucun | G28: Pas de cas dédié : session exploratoire (reprise d'une ancienne commande dont un produit est en rupture).
A30: Contrôles
A31: Risques de niveau Critique sans aucun cas | C31: =COUNTIFS($D$5:$D$28,"Critique",$E$5:$E$28,0) -> 0
A32: Risques de niveau Élevé sans aucun cas | C32: =COUNTIFS($D$5:$D$28,"Élevé",$E$5:$E$28,0) -> 0
A33: Cas de test sans risque renseigné | C33: =COUNTBLANK('Cas de test'!$D$2:$D$25) -> 0
A35: Attendu : 0 pour les trois contrôles. Les deux risques modérés sans cas sont couverts en exploration.
